{
  "shows": {
    "ALUC|471|20260405|PLATINUM": {
      "venue": "ALLU Cinemas: Kokapet",
      "time": "04:00 PM",
      "date": "20260405",
      "cat": "PLATINUM",
      "price": "350.00",
      "status": "0"
    },
    "ALUC|471|20260405|GOLD": {
      "venue": "ALLU Cinemas: Kokapet",
      "time": "04:00 PM",
      "date": "20260405",
      "cat": "GOLD",
      "price": "295.00",
      "status": "2"
    },
    "ALUC|472|20260405|PLATINUM": {
      "venue": "ALLU Cinemas: Kokapet",
      "time": "07:15 PM",
      "date": "20260405",
      "cat": "PLATINUM",
      "price": "350.00",
      "status": "0"
    },
    "ALUC|472|20260405|GOLD": {
      "venue": "ALLU Cinemas: Kokapet",
      "time": "07:15 PM",
      "date": "20260405",
      "cat": "GOLD",
      "price": "295.00",
      "status": "2"
    }
  },
  "dates": {
    "20260403": "BOOKABLE",
    "20260404": "AVAILABLE",
    "20260405": "AVAILABLE",
    "20260406": "NOT_OPEN",
    "20260407": "NOT_OPEN",
    "20260408": "NOT_OPEN",
    "20260409": "NOT_OPEN"
  }
}