{
  "shows": {
    "PVFS|38778|20260424|RECLINER": {
      "venue": "PVR: Nexus Mall Kukatpally, Hyderabad",
      "time": "11:35 AM",
      "date": "20260424",
      "cat": "RECLINER",
      "price": "350.00",
      "status": "2"
    },
    "PVFS|38778|20260424|CLASSIC": {
      "venue": "PVR: Nexus Mall Kukatpally, Hyderabad",
      "time": "11:35 AM",
      "date": "20260424",
      "cat": "CLASSIC",
      "price": "295.00",
      "status": "3"
    },
    "PVFS|38780|20260424|RECLINER": {
      "venue": "PVR: Nexus Mall Kukatpally, Hyderabad",
      "time": "05:10 PM",
      "date": "20260424",
      "cat": "RECLINER",
      "price": "350.00",
      "status": "2"
    },
    "PVFS|38780|20260424|CLASSIC": {
      "venue": "PVR: Nexus Mall Kukatpally, Hyderabad",
      "time": "05:10 PM",
      "date": "20260424",
      "cat": "CLASSIC",
      "price": "295.00",
      "status": "3"
    },
    "PVFS|38781|20260424|RECLINER": {
      "venue": "PVR: Nexus Mall Kukatpally, Hyderabad",
      "time": "08:05 PM",
      "date": "20260424",
      "cat": "RECLINER",
      "price": "350.00",
      "status": "3"
    },
    "PVFS|38781|20260424|CLASSIC": {
      "venue": "PVR: Nexus Mall Kukatpally, Hyderabad",
      "time": "08:05 PM",
      "date": "20260424",
      "cat": "CLASSIC",
      "price": "295.00",
      "status": "3"
    },
    "PVFS|38782|20260424|RECLINER": {
      "venue": "PVR: Nexus Mall Kukatpally, Hyderabad",
      "time": "11:00 PM",
      "date": "20260424",
      "cat": "RECLINER",
      "price": "350.00",
      "status": "3"
    },
    "PVFS|38782|20260424|CLASSIC": {
      "venue": "PVR: Nexus Mall Kukatpally, Hyderabad",
      "time": "11:00 PM",
      "date": "20260424",
      "cat": "CLASSIC",
      "price": "295.00",
      "status": "3"
    },
    "PIIC|26711|20260424|RECLINER ROWS": {
      "venue": "PVR Superplex Inorbit: LUXE, PXL, 4DX: Cyberabad",
      "time": "11:20 AM",
      "date": "20260424",
      "cat": "RECLINER ROWS",
      "price": "600.00",
      "status": "0"
    },
    "PIIC|26711|20260424|LOUNGERS ROWS": {
      "venue": "PVR Superplex Inorbit: LUXE, PXL, 4DX: Cyberabad",
      "time": "11:20 AM",
      "date": "20260424",
      "cat": "LOUNGERS ROWS",
      "price": "400.00",
      "status": "3"
    },
    "PIIC|26711|20260424|PRIME ROWS": {
      "venue": "PVR Superplex Inorbit: LUXE, PXL, 4DX: Cyberabad",
      "time": "11:20 AM",
      "date": "20260424",
      "cat": "PRIME ROWS",
      "price": "400.00",
      "status": "3"
    },
    "PIIC|26713|20260424|RECLINER ROWS": {
      "venue": "PVR Superplex Inorbit: LUXE, PXL, 4DX: Cyberabad",
      "time": "05:10 PM",
      "date": "20260424",
      "cat": "RECLINER ROWS",
      "price": "600.00",
      "status": "0"
    },
    "PIIC|26713|20260424|PRIME ROWS": {
      "venue": "PVR Superplex Inorbit: LUXE, PXL, 4DX: Cyberabad",
      "time": "05:10 PM",
      "date": "20260424",
      "cat": "PRIME ROWS",
      "price": "400.00",
      "status": "3"
    },
    "PIIC|26713|20260424|LOUNGERS ROWS": {
      "venue": "PVR Superplex Inorbit: LUXE, PXL, 4DX: Cyberabad",
      "time": "05:10 PM",
      "date": "20260424",
      "cat": "LOUNGERS ROWS",
      "price": "400.00",
      "status": "3"
    },
    "PIIC|26714|20260424|RECLINER ROWS": {
      "venue": "PVR Superplex Inorbit: LUXE, PXL, 4DX: Cyberabad",
      "time": "08:05 PM",
      "date": "20260424",
      "cat": "RECLINER ROWS",
      "price": "600.00",
      "status": "0"
    },
    "PIIC|26714|20260424|PRIME ROWS": {
      "venue": "PVR Superplex Inorbit: LUXE, PXL, 4DX: Cyberabad",
      "time": "08:05 PM",
      "date": "20260424",
      "cat": "PRIME ROWS",
      "price": "400.00",
      "status": "3"
    },
    "PIIC|26714|20260424|LOUNGERS ROWS": {
      "venue": "PVR Superplex Inorbit: LUXE, PXL, 4DX: Cyberabad",
      "time": "08:05 PM",
      "date": "20260424",
      "cat": "LOUNGERS ROWS",
      "price": "400.00",
      "status": "3"
    },
    "PIIC|26715|20260424|RECLINER ROWS": {
      "venue": "PVR Superplex Inorbit: LUXE, PXL, 4DX: Cyberabad",
      "time": "11:00 PM",
      "date": "20260424",
      "cat": "RECLINER ROWS",
      "price": "600.00",
      "status": "0"
    },
    "PIIC|26715|20260424|PRIME ROWS": {
      "venue": "PVR Superplex Inorbit: LUXE, PXL, 4DX: Cyberabad",
      "time": "11:00 PM",
      "date": "20260424",
      "cat": "PRIME ROWS",
      "price": "400.00",
      "status": "3"
    },
    "PIIC|26715|20260424|LOUNGERS ROWS": {
      "venue": "PVR Superplex Inorbit: LUXE, PXL, 4DX: Cyberabad",
      "time": "11:00 PM",
      "date": "20260424",
      "cat": "LOUNGERS ROWS",
      "price": "400.00",
      "status": "3"
    },
    "ILKS|3998|20260424|LOUNGER ROWS": {
      "venue": "PVR Lakeshore PXL 4K Laser ATMOS DTS-X Y Junction",
      "time": "10:50 AM",
      "date": "20260424",
      "cat": "LOUNGER ROWS",
      "price": "354.00",
      "status": "3"
    },
    "ILKS|3998|20260424|RECLINER ROWS": {
      "venue": "PVR Lakeshore PXL 4K Laser ATMOS DTS-X Y Junction",
      "time": "10:50 AM",
      "date": "20260424",
      "cat": "RECLINER ROWS",
      "price": "354.00",
      "status": "1"
    },
    "ILKS|3998|20260424|CLASSIC ROWS": {
      "venue": "PVR Lakeshore PXL 4K Laser ATMOS DTS-X Y Junction",
      "time": "10:50 AM",
      "date": "20260424",
      "cat": "CLASSIC ROWS",
      "price": "295.00",
      "status": "3"
    },
    "ILKS|3998|20260424|PRIME ROWS": {
      "venue": "PVR Lakeshore PXL 4K Laser ATMOS DTS-X Y Junction",
      "time": "10:50 AM",
      "date": "20260424",
      "cat": "PRIME ROWS",
      "price": "295.00",
      "status": "3"
    },
    "ILKS|4000|20260424|LOUNGER ROWS": {
      "venue": "PVR Lakeshore PXL 4K Laser ATMOS DTS-X Y Junction",
      "time": "04:40 PM",
      "date": "20260424",
      "cat": "LOUNGER ROWS",
      "price": "354.00",
      "status": "3"
    },
    "ILKS|4000|20260424|RECLINER ROWS": {
      "venue": "PVR Lakeshore PXL 4K Laser ATMOS DTS-X Y Junction",
      "time": "04:40 PM",
      "date": "20260424",
      "cat": "RECLINER ROWS",
      "price": "354.00",
      "status": "2"
    },
    "ILKS|4000|20260424|PRIME ROWS": {
      "venue": "PVR Lakeshore PXL 4K Laser ATMOS DTS-X Y Junction",
      "time": "04:40 PM",
      "date": "20260424",
      "cat": "PRIME ROWS",
      "price": "295.00",
      "status": "3"
    },
    "ILKS|4000|20260424|CLASSIC ROWS": {
      "venue": "PVR Lakeshore PXL 4K Laser ATMOS DTS-X Y Junction",
      "time": "04:40 PM",
      "date": "20260424",
      "cat": "CLASSIC ROWS",
      "price": "295.00",
      "status": "3"
    },
    "ILKS|4001|20260424|LOUNGER ROWS": {
      "venue": "PVR Lakeshore PXL 4K Laser ATMOS DTS-X Y Junction",
      "time": "07:35 PM",
      "date": "20260424",
      "cat": "LOUNGER ROWS",
      "price": "354.00",
      "status": "3"
    },
    "ILKS|4001|20260424|RECLINER ROWS": {
      "venue": "PVR Lakeshore PXL 4K Laser ATMOS DTS-X Y Junction",
      "time": "07:35 PM",
      "date": "20260424",
      "cat": "RECLINER ROWS",
      "price": "354.00",
      "status": "2"
    },
    "ILKS|4001|20260424|CLASSIC ROWS": {
      "venue": "PVR Lakeshore PXL 4K Laser ATMOS DTS-X Y Junction",
      "time": "07:35 PM",
      "date": "20260424",
      "cat": "CLASSIC ROWS",
      "price": "295.00",
      "status": "3"
    },
    "ILKS|4001|20260424|PRIME ROWS": {
      "venue": "PVR Lakeshore PXL 4K Laser ATMOS DTS-X Y Junction",
      "time": "07:35 PM",
      "date": "20260424",
      "cat": "PRIME ROWS",
      "price": "295.00",
      "status": "3"
    },
    "ILKS|4002|20260424|LOUNGER ROWS": {
      "venue": "PVR Lakeshore PXL 4K Laser ATMOS DTS-X Y Junction",
      "time": "10:30 PM",
      "date": "20260424",
      "cat": "LOUNGER ROWS",
      "price": "354.00",
      "status": "3"
    },
    "ILKS|4002|20260424|RECLINER ROWS": {
      "venue": "PVR Lakeshore PXL 4K Laser ATMOS DTS-X Y Junction",
      "time": "10:30 PM",
      "date": "20260424",
      "cat": "RECLINER ROWS",
      "price": "354.00",
      "status": "2"
    },
    "ILKS|4002|20260424|CLASSIC ROWS": {
      "venue": "PVR Lakeshore PXL 4K Laser ATMOS DTS-X Y Junction",
      "time": "10:30 PM",
      "date": "20260424",
      "cat": "CLASSIC ROWS",
      "price": "295.00",
      "status": "3"
    },
    "ILKS|4002|20260424|PRIME ROWS": {
      "venue": "PVR Lakeshore PXL 4K Laser ATMOS DTS-X Y Junction",
      "time": "10:30 PM",
      "date": "20260424",
      "cat": "PRIME ROWS",
      "price": "295.00",
      "status": "3"
    },
    "PNNG|34025|20260424|RECLINER": {
      "venue": "PVR: Next Galleria Mall, Panjagutta",
      "time": "11:05 AM",
      "date": "20260424",
      "cat": "RECLINER",
      "price": "350.00",
      "status": "3"
    },
    "PNNG|34025|20260424|CLASSIC": {
      "venue": "PVR: Next Galleria Mall, Panjagutta",
      "time": "11:05 AM",
      "date": "20260424",
      "cat": "CLASSIC",
      "price": "295.00",
      "status": "3"
    },
    "PNNG|34027|20260424|RECLINER": {
      "venue": "PVR: Next Galleria Mall, Panjagutta",
      "time": "04:55 PM",
      "date": "20260424",
      "cat": "RECLINER",
      "price": "350.00",
      "status": "3"
    },
    "PNNG|34027|20260424|CLASSIC": {
      "venue": "PVR: Next Galleria Mall, Panjagutta",
      "time": "04:55 PM",
      "date": "20260424",
      "cat": "CLASSIC",
      "price": "295.00",
      "status": "3"
    },
    "PNNG|34028|20260424|RECLINER": {
      "venue": "PVR: Next Galleria Mall, Panjagutta",
      "time": "07:50 PM",
      "date": "20260424",
      "cat": "RECLINER",
      "price": "350.00",
      "status": "3"
    },
    "PNNG|34028|20260424|CLASSIC": {
      "venue": "PVR: Next Galleria Mall, Panjagutta",
      "time": "07:50 PM",
      "date": "20260424",
      "cat": "CLASSIC",
      "price": "295.00",
      "status": "3"
    },
    "PNNG|34029|20260424|RECLINER": {
      "venue": "PVR: Next Galleria Mall, Panjagutta",
      "time": "10:45 PM",
      "date": "20260424",
      "cat": "RECLINER",
      "price": "350.00",
      "status": "3"
    },
    "PNNG|34029|20260424|CLASSIC": {
      "venue": "PVR: Next Galleria Mall, Panjagutta",
      "time": "10:45 PM",
      "date": "20260424",
      "cat": "CLASSIC",
      "price": "295.00",
      "status": "3"
    },
    "PVTS|20632|20260424|RECLINER": {
      "venue": "PVR: Atrium Gachibowli, Hyderabad",
      "time": "11:20 AM",
      "date": "20260424",
      "cat": "RECLINER",
      "price": "350.00",
      "status": "3"
    },
    "PVTS|20632|20260424|CLASSIC": {
      "venue": "PVR: Atrium Gachibowli, Hyderabad",
      "time": "11:20 AM",
      "date": "20260424",
      "cat": "CLASSIC",
      "price": "295.00",
      "status": "3"
    },
    "PVTS|20634|20260424|RECLINER": {
      "venue": "PVR: Atrium Gachibowli, Hyderabad",
      "time": "05:10 PM",
      "date": "20260424",
      "cat": "RECLINER",
      "price": "350.00",
      "status": "3"
    },
    "PVTS|20634|20260424|CLASSIC": {
      "venue": "PVR: Atrium Gachibowli, Hyderabad",
      "time": "05:10 PM",
      "date": "20260424",
      "cat": "CLASSIC",
      "price": "295.00",
      "status": "3"
    },
    "PVTS|20635|20260424|RECLINER": {
      "venue": "PVR: Atrium Gachibowli, Hyderabad",
      "time": "08:05 PM",
      "date": "20260424",
      "cat": "RECLINER",
      "price": "350.00",
      "status": "3"
    },
    "PVTS|20635|20260424|CLASSIC": {
      "venue": "PVR: Atrium Gachibowli, Hyderabad",
      "time": "08:05 PM",
      "date": "20260424",
      "cat": "CLASSIC",
      "price": "295.00",
      "status": "3"
    },
    "PVTS|20636|20260424|RECLINER": {
      "venue": "PVR: Atrium Gachibowli, Hyderabad",
      "time": "11:00 PM",
      "date": "20260424",
      "cat": "RECLINER",
      "price": "350.00",
      "status": "3"
    },
    "PVTS|20636|20260424|CLASSIC": {
      "venue": "PVR: Atrium Gachibowli, Hyderabad",
      "time": "11:00 PM",
      "date": "20260424",
      "cat": "CLASSIC",
      "price": "295.00",
      "status": "3"
    },
    "PVTP|16343|20260424|CLASSIC": {
      "venue": "PVR: Preston, Gachibowli Hyderabad",
      "time": "10:50 AM",
      "date": "20260424",
      "cat": "CLASSIC",
      "price": "295.00",
      "status": "3"
    },
    "PVTP|16345|20260424|CLASSIC": {
      "venue": "PVR: Preston, Gachibowli Hyderabad",
      "time": "04:40 PM",
      "date": "20260424",
      "cat": "CLASSIC",
      "price": "295.00",
      "status": "3"
    },
    "PVTP|16346|20260424|CLASSIC": {
      "venue": "PVR: Preston, Gachibowli Hyderabad",
      "time": "07:35 PM",
      "date": "20260424",
      "cat": "CLASSIC",
      "price": "295.00",
      "status": "3"
    },
    "PVTP|16347|20260424|CLASSIC": {
      "venue": "PVR: Preston, Gachibowli Hyderabad",
      "time": "10:30 PM",
      "date": "20260424",
      "cat": "CLASSIC",
      "price": "295.00",
      "status": "3"
    },
    "PVHM|23013|20260424|RECLINER": {
      "venue": "PVR ICON: Hitech, Madhapur, Hyderabad",
      "time": "11:20 AM",
      "date": "20260424",
      "cat": "RECLINER",
      "price": "350.00",
      "status": "3"
    },
    "PVHM|23013|20260424|CLASSIC": {
      "venue": "PVR ICON: Hitech, Madhapur, Hyderabad",
      "time": "11:20 AM",
      "date": "20260424",
      "cat": "CLASSIC",
      "price": "295.00",
      "status": "3"
    },
    "PVHM|23015|20260424|RECLINER": {
      "venue": "PVR ICON: Hitech, Madhapur, Hyderabad",
      "time": "05:10 PM",
      "date": "20260424",
      "cat": "RECLINER",
      "price": "350.00",
      "status": "3"
    },
    "PVHM|23015|20260424|CLASSIC": {
      "venue": "PVR ICON: Hitech, Madhapur, Hyderabad",
      "time": "05:10 PM",
      "date": "20260424",
      "cat": "CLASSIC",
      "price": "295.00",
      "status": "3"
    },
    "PVHM|23016|20260424|RECLINER": {
      "venue": "PVR ICON: Hitech, Madhapur, Hyderabad",
      "time": "08:05 PM",
      "date": "20260424",
      "cat": "RECLINER",
      "price": "350.00",
      "status": "0"
    },
    "PVHM|23016|20260424|CLASSIC": {
      "venue": "PVR ICON: Hitech, Madhapur, Hyderabad",
      "time": "08:05 PM",
      "date": "20260424",
      "cat": "CLASSIC",
      "price": "295.00",
      "status": "3"
    },
    "PVHM|23017|20260424|RECLINER": {
      "venue": "PVR ICON: Hitech, Madhapur, Hyderabad",
      "time": "11:00 PM",
      "date": "20260424",
      "cat": "RECLINER",
      "price": "350.00",
      "status": "0"
    },
    "PVHM|23017|20260424|CLASSIC": {
      "venue": "PVR ICON: Hitech, Madhapur, Hyderabad",
      "time": "11:00 PM",
      "date": "20260424",
      "cat": "CLASSIC",
      "price": "295.00",
      "status": "3"
    },
    "PVUM|24457|20260424|RECLINER": {
      "venue": "PVR: Musarambagh, Hyderabad",
      "time": "11:20 AM",
      "date": "20260424",
      "cat": "RECLINER",
      "price": "350.00",
      "status": "3"
    },
    "PVUM|24457|20260424|CLASSIC": {
      "venue": "PVR: Musarambagh, Hyderabad",
      "time": "11:20 AM",
      "date": "20260424",
      "cat": "CLASSIC",
      "price": "295.00",
      "status": "3"
    },
    "PVUM|24459|20260424|RECLINER": {
      "venue": "PVR: Musarambagh, Hyderabad",
      "time": "05:10 PM",
      "date": "20260424",
      "cat": "RECLINER",
      "price": "350.00",
      "status": "3"
    },
    "PVUM|24459|20260424|CLASSIC": {
      "venue": "PVR: Musarambagh, Hyderabad",
      "time": "05:10 PM",
      "date": "20260424",
      "cat": "CLASSIC",
      "price": "295.00",
      "status": "3"
    },
    "PVUM|24460|20260424|RECLINER": {
      "venue": "PVR: Musarambagh, Hyderabad",
      "time": "08:05 PM",
      "date": "20260424",
      "cat": "RECLINER",
      "price": "350.00",
      "status": "3"
    },
    "PVUM|24460|20260424|CLASSIC": {
      "venue": "PVR: Musarambagh, Hyderabad",
      "time": "08:05 PM",
      "date": "20260424",
      "cat": "CLASSIC",
      "price": "295.00",
      "status": "3"
    },
    "PVUM|24461|20260424|RECLINER": {
      "venue": "PVR: Musarambagh, Hyderabad",
      "time": "11:00 PM",
      "date": "20260424",
      "cat": "RECLINER",
      "price": "350.00",
      "status": "3"
    },
    "PVUM|24461|20260424|CLASSIC": {
      "venue": "PVR: Musarambagh, Hyderabad",
      "time": "11:00 PM",
      "date": "20260424",
      "cat": "CLASSIC",
      "price": "295.00",
      "status": "3"
    },
    "PVFS|38783|20260425|RECLINER": {
      "venue": "PVR: Nexus Mall Kukatpally, Hyderabad",
      "time": "11:35 AM",
      "date": "20260425",
      "cat": "RECLINER",
      "price": "350.00",
      "status": "2"
    },
    "PVFS|38783|20260425|CLASSIC": {
      "venue": "PVR: Nexus Mall Kukatpally, Hyderabad",
      "time": "11:35 AM",
      "date": "20260425",
      "cat": "CLASSIC",
      "price": "295.00",
      "status": "3"
    },
    "PVFS|38785|20260425|RECLINER": {
      "venue": "PVR: Nexus Mall Kukatpally, Hyderabad",
      "time": "05:10 PM",
      "date": "20260425",
      "cat": "RECLINER",
      "price": "350.00",
      "status": "3"
    },
    "PVFS|38785|20260425|CLASSIC": {
      "venue": "PVR: Nexus Mall Kukatpally, Hyderabad",
      "time": "05:10 PM",
      "date": "20260425",
      "cat": "CLASSIC",
      "price": "295.00",
      "status": "3"
    },
    "PVFS|38786|20260425|RECLINER": {
      "venue": "PVR: Nexus Mall Kukatpally, Hyderabad",
      "time": "08:05 PM",
      "date": "20260425",
      "cat": "RECLINER",
      "price": "350.00",
      "status": "2"
    },
    "PVFS|38786|20260425|CLASSIC": {
      "venue": "PVR: Nexus Mall Kukatpally, Hyderabad",
      "time": "08:05 PM",
      "date": "20260425",
      "cat": "CLASSIC",
      "price": "295.00",
      "status": "3"
    },
    "PVFS|38787|20260425|RECLINER": {
      "venue": "PVR: Nexus Mall Kukatpally, Hyderabad",
      "time": "11:00 PM",
      "date": "20260425",
      "cat": "RECLINER",
      "price": "350.00",
      "status": "3"
    },
    "PVFS|38787|20260425|CLASSIC": {
      "venue": "PVR: Nexus Mall Kukatpally, Hyderabad",
      "time": "11:00 PM",
      "date": "20260425",
      "cat": "CLASSIC",
      "price": "295.00",
      "status": "3"
    },
    "PIIC|26727|20260425|RECLINER ROWS": {
      "venue": "PVR Superplex Inorbit: LUXE, PXL, 4DX: Cyberabad",
      "time": "11:20 AM",
      "date": "20260425",
      "cat": "RECLINER ROWS",
      "price": "600.00",
      "status": "0"
    },
    "PIIC|26727|20260425|PRIME ROWS": {
      "venue": "PVR Superplex Inorbit: LUXE, PXL, 4DX: Cyberabad",
      "time": "11:20 AM",
      "date": "20260425",
      "cat": "PRIME ROWS",
      "price": "400.00",
      "status": "3"
    },
    "PIIC|26727|20260425|LOUNGERS ROWS": {
      "venue": "PVR Superplex Inorbit: LUXE, PXL, 4DX: Cyberabad",
      "time": "11:20 AM",
      "date": "20260425",
      "cat": "LOUNGERS ROWS",
      "price": "400.00",
      "status": "3"
    },
    "PIIC|26729|20260425|RECLINER ROWS": {
      "venue": "PVR Superplex Inorbit: LUXE, PXL, 4DX: Cyberabad",
      "time": "05:10 PM",
      "date": "20260425",
      "cat": "RECLINER ROWS",
      "price": "600.00",
      "status": "0"
    },
    "PIIC|26729|20260425|LOUNGERS ROWS": {
      "venue": "PVR Superplex Inorbit: LUXE, PXL, 4DX: Cyberabad",
      "time": "05:10 PM",
      "date": "20260425",
      "cat": "LOUNGERS ROWS",
      "price": "400.00",
      "status": "3"
    },
    "PIIC|26729|20260425|PRIME ROWS": {
      "venue": "PVR Superplex Inorbit: LUXE, PXL, 4DX: Cyberabad",
      "time": "05:10 PM",
      "date": "20260425",
      "cat": "PRIME ROWS",
      "price": "400.00",
      "status": "3"
    },
    "PIIC|26730|20260425|RECLINER ROWS": {
      "venue": "PVR Superplex Inorbit: LUXE, PXL, 4DX: Cyberabad",
      "time": "08:05 PM",
      "date": "20260425",
      "cat": "RECLINER ROWS",
      "price": "600.00",
      "status": "0"
    },
    "PIIC|26730|20260425|LOUNGERS ROWS": {
      "venue": "PVR Superplex Inorbit: LUXE, PXL, 4DX: Cyberabad",
      "time": "08:05 PM",
      "date": "20260425",
      "cat": "LOUNGERS ROWS",
      "price": "400.00",
      "status": "3"
    },
    "PIIC|26730|20260425|PRIME ROWS": {
      "venue": "PVR Superplex Inorbit: LUXE, PXL, 4DX: Cyberabad",
      "time": "08:05 PM",
      "date": "20260425",
      "cat": "PRIME ROWS",
      "price": "400.00",
      "status": "3"
    },
    "PIIC|26731|20260425|RECLINER ROWS": {
      "venue": "PVR Superplex Inorbit: LUXE, PXL, 4DX: Cyberabad",
      "time": "11:00 PM",
      "date": "20260425",
      "cat": "RECLINER ROWS",
      "price": "600.00",
      "status": "0"
    },
    "PIIC|26731|20260425|PRIME ROWS": {
      "venue": "PVR Superplex Inorbit: LUXE, PXL, 4DX: Cyberabad",
      "time": "11:00 PM",
      "date": "20260425",
      "cat": "PRIME ROWS",
      "price": "400.00",
      "status": "3"
    },
    "PIIC|26731|20260425|LOUNGERS ROWS": {
      "venue": "PVR Superplex Inorbit: LUXE, PXL, 4DX: Cyberabad",
      "time": "11:00 PM",
      "date": "20260425",
      "cat": "LOUNGERS ROWS",
      "price": "400.00",
      "status": "3"
    },
    "ILKS|4003|20260425|RECLINER ROWS": {
      "venue": "PVR Lakeshore PXL 4K Laser ATMOS DTS-X Y Junction",
      "time": "10:50 AM",
      "date": "20260425",
      "cat": "RECLINER ROWS",
      "price": "354.00",
      "status": "3"
    },
    "ILKS|4003|20260425|LOUNGER ROWS": {
      "venue": "PVR Lakeshore PXL 4K Laser ATMOS DTS-X Y Junction",
      "time": "10:50 AM",
      "date": "20260425",
      "cat": "LOUNGER ROWS",
      "price": "354.00",
      "status": "3"
    },
    "ILKS|4003|20260425|CLASSIC ROWS": {
      "venue": "PVR Lakeshore PXL 4K Laser ATMOS DTS-X Y Junction",
      "time": "10:50 AM",
      "date": "20260425",
      "cat": "CLASSIC ROWS",
      "price": "295.00",
      "status": "3"
    },
    "ILKS|4003|20260425|PRIME ROWS": {
      "venue": "PVR Lakeshore PXL 4K Laser ATMOS DTS-X Y Junction",
      "time": "10:50 AM",
      "date": "20260425",
      "cat": "PRIME ROWS",
      "price": "295.00",
      "status": "3"
    },
    "ILKS|4005|20260425|LOUNGER ROWS": {
      "venue": "PVR Lakeshore PXL 4K Laser ATMOS DTS-X Y Junction",
      "time": "04:40 PM",
      "date": "20260425",
      "cat": "LOUNGER ROWS",
      "price": "354.00",
      "status": "3"
    },
    "ILKS|4005|20260425|RECLINER ROWS": {
      "venue": "PVR Lakeshore PXL 4K Laser ATMOS DTS-X Y Junction",
      "time": "04:40 PM",
      "date": "20260425",
      "cat": "RECLINER ROWS",
      "price": "354.00",
      "status": "1"
    },
    "ILKS|4005|20260425|CLASSIC ROWS": {
      "venue": "PVR Lakeshore PXL 4K Laser ATMOS DTS-X Y Junction",
      "time": "04:40 PM",
      "date": "20260425",
      "cat": "CLASSIC ROWS",
      "price": "295.00",
      "status": "3"
    },
    "ILKS|4005|20260425|PRIME ROWS": {
      "venue": "PVR Lakeshore PXL 4K Laser ATMOS DTS-X Y Junction",
      "time": "04:40 PM",
      "date": "20260425",
      "cat": "PRIME ROWS",
      "price": "295.00",
      "status": "3"
    },
    "ILKS|4006|20260425|LOUNGER ROWS": {
      "venue": "PVR Lakeshore PXL 4K Laser ATMOS DTS-X Y Junction",
      "time": "07:35 PM",
      "date": "20260425",
      "cat": "LOUNGER ROWS",
      "price": "354.00",
      "status": "3"
    },
    "ILKS|4006|20260425|RECLINER ROWS": {
      "venue": "PVR Lakeshore PXL 4K Laser ATMOS DTS-X Y Junction",
      "time": "07:35 PM",
      "date": "20260425",
      "cat": "RECLINER ROWS",
      "price": "354.00",
      "status": "2"
    },
    "ILKS|4006|20260425|CLASSIC ROWS": {
      "venue": "PVR Lakeshore PXL 4K Laser ATMOS DTS-X Y Junction",
      "time": "07:35 PM",
      "date": "20260425",
      "cat": "CLASSIC ROWS",
      "price": "295.00",
      "status": "3"
    },
    "ILKS|4006|20260425|PRIME ROWS": {
      "venue": "PVR Lakeshore PXL 4K Laser ATMOS DTS-X Y Junction",
      "time": "07:35 PM",
      "date": "20260425",
      "cat": "PRIME ROWS",
      "price": "295.00",
      "status": "3"
    },
    "ILKS|4007|20260425|LOUNGER ROWS": {
      "venue": "PVR Lakeshore PXL 4K Laser ATMOS DTS-X Y Junction",
      "time": "10:30 PM",
      "date": "20260425",
      "cat": "LOUNGER ROWS",
      "price": "354.00",
      "status": "3"
    },
    "ILKS|4007|20260425|RECLINER ROWS": {
      "venue": "PVR Lakeshore PXL 4K Laser ATMOS DTS-X Y Junction",
      "time": "10:30 PM",
      "date": "20260425",
      "cat": "RECLINER ROWS",
      "price": "354.00",
      "status": "3"
    },
    "ILKS|4007|20260425|PRIME ROWS": {
      "venue": "PVR Lakeshore PXL 4K Laser ATMOS DTS-X Y Junction",
      "time": "10:30 PM",
      "date": "20260425",
      "cat": "PRIME ROWS",
      "price": "295.00",
      "status": "3"
    },
    "ILKS|4007|20260425|CLASSIC ROWS": {
      "venue": "PVR Lakeshore PXL 4K Laser ATMOS DTS-X Y Junction",
      "time": "10:30 PM",
      "date": "20260425",
      "cat": "CLASSIC ROWS",
      "price": "295.00",
      "status": "3"
    },
    "PNNG|34030|20260425|RECLINER": {
      "venue": "PVR: Next Galleria Mall, Panjagutta",
      "time": "11:05 AM",
      "date": "20260425",
      "cat": "RECLINER",
      "price": "350.00",
      "status": "3"
    },
    "PNNG|34030|20260425|CLASSIC": {
      "venue": "PVR: Next Galleria Mall, Panjagutta",
      "time": "11:05 AM",
      "date": "20260425",
      "cat": "CLASSIC",
      "price": "295.00",
      "status": "3"
    },
    "PNNG|34032|20260425|RECLINER": {
      "venue": "PVR: Next Galleria Mall, Panjagutta",
      "time": "04:55 PM",
      "date": "20260425",
      "cat": "RECLINER",
      "price": "350.00",
      "status": "3"
    },
    "PNNG|34032|20260425|CLASSIC": {
      "venue": "PVR: Next Galleria Mall, Panjagutta",
      "time": "04:55 PM",
      "date": "20260425",
      "cat": "CLASSIC",
      "price": "295.00",
      "status": "3"
    },
    "PNNG|34033|20260425|RECLINER": {
      "venue": "PVR: Next Galleria Mall, Panjagutta",
      "time": "07:50 PM",
      "date": "20260425",
      "cat": "RECLINER",
      "price": "350.00",
      "status": "3"
    },
    "PNNG|34033|20260425|CLASSIC": {
      "venue": "PVR: Next Galleria Mall, Panjagutta",
      "time": "07:50 PM",
      "date": "20260425",
      "cat": "CLASSIC",
      "price": "295.00",
      "status": "3"
    },
    "PNNG|34034|20260425|RECLINER": {
      "venue": "PVR: Next Galleria Mall, Panjagutta",
      "time": "10:45 PM",
      "date": "20260425",
      "cat": "RECLINER",
      "price": "350.00",
      "status": "3"
    },
    "PNNG|34034|20260425|CLASSIC": {
      "venue": "PVR: Next Galleria Mall, Panjagutta",
      "time": "10:45 PM",
      "date": "20260425",
      "cat": "CLASSIC",
      "price": "295.00",
      "status": "3"
    },
    "PVTS|20710|20260425|RECLINER": {
      "venue": "PVR: Atrium Gachibowli, Hyderabad",
      "time": "11:20 AM",
      "date": "20260425",
      "cat": "RECLINER",
      "price": "350.00",
      "status": "3"
    },
    "PVTS|20710|20260425|CLASSIC": {
      "venue": "PVR: Atrium Gachibowli, Hyderabad",
      "time": "11:20 AM",
      "date": "20260425",
      "cat": "CLASSIC",
      "price": "295.00",
      "status": "3"
    },
    "PVTS|20712|20260425|RECLINER": {
      "venue": "PVR: Atrium Gachibowli, Hyderabad",
      "time": "05:10 PM",
      "date": "20260425",
      "cat": "RECLINER",
      "price": "350.00",
      "status": "3"
    },
    "PVTS|20712|20260425|CLASSIC": {
      "venue": "PVR: Atrium Gachibowli, Hyderabad",
      "time": "05:10 PM",
      "date": "20260425",
      "cat": "CLASSIC",
      "price": "295.00",
      "status": "3"
    },
    "PVTS|20713|20260425|RECLINER": {
      "venue": "PVR: Atrium Gachibowli, Hyderabad",
      "time": "08:05 PM",
      "date": "20260425",
      "cat": "RECLINER",
      "price": "350.00",
      "status": "3"
    },
    "PVTS|20713|20260425|CLASSIC": {
      "venue": "PVR: Atrium Gachibowli, Hyderabad",
      "time": "08:05 PM",
      "date": "20260425",
      "cat": "CLASSIC",
      "price": "295.00",
      "status": "3"
    },
    "PVTS|20714|20260425|RECLINER": {
      "venue": "PVR: Atrium Gachibowli, Hyderabad",
      "time": "11:00 PM",
      "date": "20260425",
      "cat": "RECLINER",
      "price": "350.00",
      "status": "3"
    },
    "PVTS|20714|20260425|CLASSIC": {
      "venue": "PVR: Atrium Gachibowli, Hyderabad",
      "time": "11:00 PM",
      "date": "20260425",
      "cat": "CLASSIC",
      "price": "295.00",
      "status": "3"
    },
    "PVTP|16348|20260425|CLASSIC": {
      "venue": "PVR: Preston, Gachibowli Hyderabad",
      "time": "10:50 AM",
      "date": "20260425",
      "cat": "CLASSIC",
      "price": "295.00",
      "status": "3"
    },
    "PVTP|16350|20260425|CLASSIC": {
      "venue": "PVR: Preston, Gachibowli Hyderabad",
      "time": "04:40 PM",
      "date": "20260425",
      "cat": "CLASSIC",
      "price": "295.00",
      "status": "3"
    },
    "PVTP|16351|20260425|CLASSIC": {
      "venue": "PVR: Preston, Gachibowli Hyderabad",
      "time": "07:35 PM",
      "date": "20260425",
      "cat": "CLASSIC",
      "price": "295.00",
      "status": "3"
    },
    "PVTP|16352|20260425|CLASSIC": {
      "venue": "PVR: Preston, Gachibowli Hyderabad",
      "time": "10:30 PM",
      "date": "20260425",
      "cat": "CLASSIC",
      "price": "295.00",
      "status": "3"
    },
    "PVHM|23018|20260425|RECLINER": {
      "venue": "PVR ICON: Hitech, Madhapur, Hyderabad",
      "time": "11:20 AM",
      "date": "20260425",
      "cat": "RECLINER",
      "price": "350.00",
      "status": "3"
    },
    "PVHM|23018|20260425|CLASSIC": {
      "venue": "PVR ICON: Hitech, Madhapur, Hyderabad",
      "time": "11:20 AM",
      "date": "20260425",
      "cat": "CLASSIC",
      "price": "295.00",
      "status": "3"
    },
    "PVHM|23020|20260425|RECLINER": {
      "venue": "PVR ICON: Hitech, Madhapur, Hyderabad",
      "time": "05:10 PM",
      "date": "20260425",
      "cat": "RECLINER",
      "price": "350.00",
      "status": "3"
    },
    "PVHM|23020|20260425|CLASSIC": {
      "venue": "PVR ICON: Hitech, Madhapur, Hyderabad",
      "time": "05:10 PM",
      "date": "20260425",
      "cat": "CLASSIC",
      "price": "295.00",
      "status": "3"
    },
    "PVHM|23021|20260425|RECLINER": {
      "venue": "PVR ICON: Hitech, Madhapur, Hyderabad",
      "time": "08:05 PM",
      "date": "20260425",
      "cat": "RECLINER",
      "price": "350.00",
      "status": "0"
    },
    "PVHM|23021|20260425|CLASSIC": {
      "venue": "PVR ICON: Hitech, Madhapur, Hyderabad",
      "time": "08:05 PM",
      "date": "20260425",
      "cat": "CLASSIC",
      "price": "295.00",
      "status": "3"
    },
    "PVHM|23022|20260425|RECLINER": {
      "venue": "PVR ICON: Hitech, Madhapur, Hyderabad",
      "time": "11:00 PM",
      "date": "20260425",
      "cat": "RECLINER",
      "price": "350.00",
      "status": "0"
    },
    "PVHM|23022|20260425|CLASSIC": {
      "venue": "PVR ICON: Hitech, Madhapur, Hyderabad",
      "time": "11:00 PM",
      "date": "20260425",
      "cat": "CLASSIC",
      "price": "295.00",
      "status": "3"
    },
    "PVUM|24543|20260425|RECLINER": {
      "venue": "PVR: Musarambagh, Hyderabad",
      "time": "11:20 AM",
      "date": "20260425",
      "cat": "RECLINER",
      "price": "350.00",
      "status": "3"
    },
    "PVUM|24543|20260425|CLASSIC": {
      "venue": "PVR: Musarambagh, Hyderabad",
      "time": "11:20 AM",
      "date": "20260425",
      "cat": "CLASSIC",
      "price": "295.00",
      "status": "3"
    },
    "PVUM|24545|20260425|RECLINER": {
      "venue": "PVR: Musarambagh, Hyderabad",
      "time": "05:10 PM",
      "date": "20260425",
      "cat": "RECLINER",
      "price": "350.00",
      "status": "3"
    },
    "PVUM|24545|20260425|CLASSIC": {
      "venue": "PVR: Musarambagh, Hyderabad",
      "time": "05:10 PM",
      "date": "20260425",
      "cat": "CLASSIC",
      "price": "295.00",
      "status": "3"
    },
    "PVUM|24546|20260425|RECLINER": {
      "venue": "PVR: Musarambagh, Hyderabad",
      "time": "08:05 PM",
      "date": "20260425",
      "cat": "RECLINER",
      "price": "350.00",
      "status": "3"
    },
    "PVUM|24546|20260425|CLASSIC": {
      "venue": "PVR: Musarambagh, Hyderabad",
      "time": "08:05 PM",
      "date": "20260425",
      "cat": "CLASSIC",
      "price": "295.00",
      "status": "3"
    },
    "PVUM|24547|20260425|RECLINER": {
      "venue": "PVR: Musarambagh, Hyderabad",
      "time": "11:00 PM",
      "date": "20260425",
      "cat": "RECLINER",
      "price": "350.00",
      "status": "3"
    },
    "PVUM|24547|20260425|CLASSIC": {
      "venue": "PVR: Musarambagh, Hyderabad",
      "time": "11:00 PM",
      "date": "20260425",
      "cat": "CLASSIC",
      "price": "295.00",
      "status": "3"
    },
    "PVFS|38788|20260426|RECLINER": {
      "venue": "PVR: Nexus Mall Kukatpally, Hyderabad",
      "time": "11:35 AM",
      "date": "20260426",
      "cat": "RECLINER",
      "price": "350.00",
      "status": "2"
    },
    "PVFS|38788|20260426|CLASSIC": {
      "venue": "PVR: Nexus Mall Kukatpally, Hyderabad",
      "time": "11:35 AM",
      "date": "20260426",
      "cat": "CLASSIC",
      "price": "295.00",
      "status": "3"
    },
    "PVFS|38790|20260426|RECLINER": {
      "venue": "PVR: Nexus Mall Kukatpally, Hyderabad",
      "time": "05:10 PM",
      "date": "20260426",
      "cat": "RECLINER",
      "price": "350.00",
      "status": "3"
    },
    "PVFS|38790|20260426|CLASSIC": {
      "venue": "PVR: Nexus Mall Kukatpally, Hyderabad",
      "time": "05:10 PM",
      "date": "20260426",
      "cat": "CLASSIC",
      "price": "295.00",
      "status": "3"
    },
    "PVFS|38791|20260426|RECLINER": {
      "venue": "PVR: Nexus Mall Kukatpally, Hyderabad",
      "time": "08:05 PM",
      "date": "20260426",
      "cat": "RECLINER",
      "price": "350.00",
      "status": "3"
    },
    "PVFS|38791|20260426|CLASSIC": {
      "venue": "PVR: Nexus Mall Kukatpally, Hyderabad",
      "time": "08:05 PM",
      "date": "20260426",
      "cat": "CLASSIC",
      "price": "295.00",
      "status": "3"
    },
    "PVFS|38792|20260426|RECLINER": {
      "venue": "PVR: Nexus Mall Kukatpally, Hyderabad",
      "time": "11:00 PM",
      "date": "20260426",
      "cat": "RECLINER",
      "price": "350.00",
      "status": "3"
    },
    "PVFS|38792|20260426|CLASSIC": {
      "venue": "PVR: Nexus Mall Kukatpally, Hyderabad",
      "time": "11:00 PM",
      "date": "20260426",
      "cat": "CLASSIC",
      "price": "295.00",
      "status": "3"
    },
    "PIIC|26734|20260426|RECLINER ROWS": {
      "venue": "PVR Superplex Inorbit: LUXE, PXL, 4DX: Cyberabad",
      "time": "05:10 PM",
      "date": "20260426",
      "cat": "RECLINER ROWS",
      "price": "600.00",
      "status": "0"
    },
    "PIIC|26734|20260426|PRIME ROWS": {
      "venue": "PVR Superplex Inorbit: LUXE, PXL, 4DX: Cyberabad",
      "time": "05:10 PM",
      "date": "20260426",
      "cat": "PRIME ROWS",
      "price": "400.00",
      "status": "3"
    },
    "PIIC|26734|20260426|LOUNGERS ROWS": {
      "venue": "PVR Superplex Inorbit: LUXE, PXL, 4DX: Cyberabad",
      "time": "05:10 PM",
      "date": "20260426",
      "cat": "LOUNGERS ROWS",
      "price": "400.00",
      "status": "3"
    },
    "PIIC|26735|20260426|RECLINER ROWS": {
      "venue": "PVR Superplex Inorbit: LUXE, PXL, 4DX: Cyberabad",
      "time": "08:05 PM",
      "date": "20260426",
      "cat": "RECLINER ROWS",
      "price": "600.00",
      "status": "0"
    },
    "PIIC|26735|20260426|LOUNGERS ROWS": {
      "venue": "PVR Superplex Inorbit: LUXE, PXL, 4DX: Cyberabad",
      "time": "08:05 PM",
      "date": "20260426",
      "cat": "LOUNGERS ROWS",
      "price": "400.00",
      "status": "3"
    },
    "PIIC|26735|20260426|PRIME ROWS": {
      "venue": "PVR Superplex Inorbit: LUXE, PXL, 4DX: Cyberabad",
      "time": "08:05 PM",
      "date": "20260426",
      "cat": "PRIME ROWS",
      "price": "400.00",
      "status": "3"
    },
    "PIIC|26736|20260426|RECLINER ROWS": {
      "venue": "PVR Superplex Inorbit: LUXE, PXL, 4DX: Cyberabad",
      "time": "11:00 PM",
      "date": "20260426",
      "cat": "RECLINER ROWS",
      "price": "600.00",
      "status": "0"
    },
    "PIIC|26736|20260426|LOUNGERS ROWS": {
      "venue": "PVR Superplex Inorbit: LUXE, PXL, 4DX: Cyberabad",
      "time": "11:00 PM",
      "date": "20260426",
      "cat": "LOUNGERS ROWS",
      "price": "400.00",
      "status": "3"
    },
    "PIIC|26736|20260426|PRIME ROWS": {
      "venue": "PVR Superplex Inorbit: LUXE, PXL, 4DX: Cyberabad",
      "time": "11:00 PM",
      "date": "20260426",
      "cat": "PRIME ROWS",
      "price": "400.00",
      "status": "3"
    },
    "ILKS|4008|20260426|LOUNGER ROWS": {
      "venue": "PVR Lakeshore PXL 4K Laser ATMOS DTS-X Y Junction",
      "time": "10:50 AM",
      "date": "20260426",
      "cat": "LOUNGER ROWS",
      "price": "354.00",
      "status": "3"
    },
    "ILKS|4008|20260426|RECLINER ROWS": {
      "venue": "PVR Lakeshore PXL 4K Laser ATMOS DTS-X Y Junction",
      "time": "10:50 AM",
      "date": "20260426",
      "cat": "RECLINER ROWS",
      "price": "354.00",
      "status": "3"
    },
    "ILKS|4008|20260426|PRIME ROWS": {
      "venue": "PVR Lakeshore PXL 4K Laser ATMOS DTS-X Y Junction",
      "time": "10:50 AM",
      "date": "20260426",
      "cat": "PRIME ROWS",
      "price": "295.00",
      "status": "3"
    },
    "ILKS|4008|20260426|CLASSIC ROWS": {
      "venue": "PVR Lakeshore PXL 4K Laser ATMOS DTS-X Y Junction",
      "time": "10:50 AM",
      "date": "20260426",
      "cat": "CLASSIC ROWS",
      "price": "295.00",
      "status": "3"
    },
    "ILKS|4010|20260426|LOUNGER ROWS": {
      "venue": "PVR Lakeshore PXL 4K Laser ATMOS DTS-X Y Junction",
      "time": "04:40 PM",
      "date": "20260426",
      "cat": "LOUNGER ROWS",
      "price": "354.00",
      "status": "3"
    },
    "ILKS|4010|20260426|RECLINER ROWS": {
      "venue": "PVR Lakeshore PXL 4K Laser ATMOS DTS-X Y Junction",
      "time": "04:40 PM",
      "date": "20260426",
      "cat": "RECLINER ROWS",
      "price": "354.00",
      "status": "3"
    },
    "ILKS|4010|20260426|CLASSIC ROWS": {
      "venue": "PVR Lakeshore PXL 4K Laser ATMOS DTS-X Y Junction",
      "time": "04:40 PM",
      "date": "20260426",
      "cat": "CLASSIC ROWS",
      "price": "295.00",
      "status": "3"
    },
    "ILKS|4010|20260426|PRIME ROWS": {
      "venue": "PVR Lakeshore PXL 4K Laser ATMOS DTS-X Y Junction",
      "time": "04:40 PM",
      "date": "20260426",
      "cat": "PRIME ROWS",
      "price": "295.00",
      "status": "3"
    },
    "ILKS|4011|20260426|RECLINER ROWS": {
      "venue": "PVR Lakeshore PXL 4K Laser ATMOS DTS-X Y Junction",
      "time": "07:35 PM",
      "date": "20260426",
      "cat": "RECLINER ROWS",
      "price": "354.00",
      "status": "3"
    },
    "ILKS|4011|20260426|LOUNGER ROWS": {
      "venue": "PVR Lakeshore PXL 4K Laser ATMOS DTS-X Y Junction",
      "time": "07:35 PM",
      "date": "20260426",
      "cat": "LOUNGER ROWS",
      "price": "354.00",
      "status": "3"
    },
    "ILKS|4011|20260426|CLASSIC ROWS": {
      "venue": "PVR Lakeshore PXL 4K Laser ATMOS DTS-X Y Junction",
      "time": "07:35 PM",
      "date": "20260426",
      "cat": "CLASSIC ROWS",
      "price": "295.00",
      "status": "3"
    },
    "ILKS|4011|20260426|PRIME ROWS": {
      "venue": "PVR Lakeshore PXL 4K Laser ATMOS DTS-X Y Junction",
      "time": "07:35 PM",
      "date": "20260426",
      "cat": "PRIME ROWS",
      "price": "295.00",
      "status": "3"
    },
    "ILKS|4012|20260426|LOUNGER ROWS": {
      "venue": "PVR Lakeshore PXL 4K Laser ATMOS DTS-X Y Junction",
      "time": "10:30 PM",
      "date": "20260426",
      "cat": "LOUNGER ROWS",
      "price": "354.00",
      "status": "3"
    },
    "ILKS|4012|20260426|RECLINER ROWS": {
      "venue": "PVR Lakeshore PXL 4K Laser ATMOS DTS-X Y Junction",
      "time": "10:30 PM",
      "date": "20260426",
      "cat": "RECLINER ROWS",
      "price": "354.00",
      "status": "3"
    },
    "ILKS|4012|20260426|CLASSIC ROWS": {
      "venue": "PVR Lakeshore PXL 4K Laser ATMOS DTS-X Y Junction",
      "time": "10:30 PM",
      "date": "20260426",
      "cat": "CLASSIC ROWS",
      "price": "295.00",
      "status": "3"
    },
    "ILKS|4012|20260426|PRIME ROWS": {
      "venue": "PVR Lakeshore PXL 4K Laser ATMOS DTS-X Y Junction",
      "time": "10:30 PM",
      "date": "20260426",
      "cat": "PRIME ROWS",
      "price": "295.00",
      "status": "3"
    },
    "PNNG|34035|20260426|RECLINER": {
      "venue": "PVR: Next Galleria Mall, Panjagutta",
      "time": "11:05 AM",
      "date": "20260426",
      "cat": "RECLINER",
      "price": "350.00",
      "status": "3"
    },
    "PNNG|34035|20260426|CLASSIC": {
      "venue": "PVR: Next Galleria Mall, Panjagutta",
      "time": "11:05 AM",
      "date": "20260426",
      "cat": "CLASSIC",
      "price": "295.00",
      "status": "3"
    },
    "PNNG|34037|20260426|RECLINER": {
      "venue": "PVR: Next Galleria Mall, Panjagutta",
      "time": "04:55 PM",
      "date": "20260426",
      "cat": "RECLINER",
      "price": "350.00",
      "status": "3"
    },
    "PNNG|34037|20260426|CLASSIC": {
      "venue": "PVR: Next Galleria Mall, Panjagutta",
      "time": "04:55 PM",
      "date": "20260426",
      "cat": "CLASSIC",
      "price": "295.00",
      "status": "3"
    },
    "PNNG|34038|20260426|RECLINER": {
      "venue": "PVR: Next Galleria Mall, Panjagutta",
      "time": "07:50 PM",
      "date": "20260426",
      "cat": "RECLINER",
      "price": "350.00",
      "status": "3"
    },
    "PNNG|34038|20260426|CLASSIC": {
      "venue": "PVR: Next Galleria Mall, Panjagutta",
      "time": "07:50 PM",
      "date": "20260426",
      "cat": "CLASSIC",
      "price": "295.00",
      "status": "3"
    },
    "PNNG|34039|20260426|RECLINER": {
      "venue": "PVR: Next Galleria Mall, Panjagutta",
      "time": "10:45 PM",
      "date": "20260426",
      "cat": "RECLINER",
      "price": "350.00",
      "status": "3"
    },
    "PNNG|34039|20260426|CLASSIC": {
      "venue": "PVR: Next Galleria Mall, Panjagutta",
      "time": "10:45 PM",
      "date": "20260426",
      "cat": "CLASSIC",
      "price": "295.00",
      "status": "3"
    },
    "PVTS|20715|20260426|RECLINER": {
      "venue": "PVR: Atrium Gachibowli, Hyderabad",
      "time": "11:20 AM",
      "date": "20260426",
      "cat": "RECLINER",
      "price": "350.00",
      "status": "3"
    },
    "PVTS|20715|20260426|CLASSIC": {
      "venue": "PVR: Atrium Gachibowli, Hyderabad",
      "time": "11:20 AM",
      "date": "20260426",
      "cat": "CLASSIC",
      "price": "295.00",
      "status": "3"
    },
    "PVTS|20717|20260426|RECLINER": {
      "venue": "PVR: Atrium Gachibowli, Hyderabad",
      "time": "05:10 PM",
      "date": "20260426",
      "cat": "RECLINER",
      "price": "350.00",
      "status": "3"
    },
    "PVTS|20717|20260426|CLASSIC": {
      "venue": "PVR: Atrium Gachibowli, Hyderabad",
      "time": "05:10 PM",
      "date": "20260426",
      "cat": "CLASSIC",
      "price": "295.00",
      "status": "3"
    },
    "PVTS|20718|20260426|RECLINER": {
      "venue": "PVR: Atrium Gachibowli, Hyderabad",
      "time": "08:05 PM",
      "date": "20260426",
      "cat": "RECLINER",
      "price": "350.00",
      "status": "3"
    },
    "PVTS|20718|20260426|CLASSIC": {
      "venue": "PVR: Atrium Gachibowli, Hyderabad",
      "time": "08:05 PM",
      "date": "20260426",
      "cat": "CLASSIC",
      "price": "295.00",
      "status": "3"
    },
    "PVTS|20719|20260426|RECLINER": {
      "venue": "PVR: Atrium Gachibowli, Hyderabad",
      "time": "11:00 PM",
      "date": "20260426",
      "cat": "RECLINER",
      "price": "350.00",
      "status": "3"
    },
    "PVTS|20719|20260426|CLASSIC": {
      "venue": "PVR: Atrium Gachibowli, Hyderabad",
      "time": "11:00 PM",
      "date": "20260426",
      "cat": "CLASSIC",
      "price": "295.00",
      "status": "3"
    },
    "PVTP|16353|20260426|CLASSIC": {
      "venue": "PVR: Preston, Gachibowli Hyderabad",
      "time": "10:50 AM",
      "date": "20260426",
      "cat": "CLASSIC",
      "price": "295.00",
      "status": "3"
    },
    "PVTP|16355|20260426|CLASSIC": {
      "venue": "PVR: Preston, Gachibowli Hyderabad",
      "time": "04:40 PM",
      "date": "20260426",
      "cat": "CLASSIC",
      "price": "295.00",
      "status": "3"
    },
    "PVTP|16356|20260426|CLASSIC": {
      "venue": "PVR: Preston, Gachibowli Hyderabad",
      "time": "07:35 PM",
      "date": "20260426",
      "cat": "CLASSIC",
      "price": "295.00",
      "status": "3"
    },
    "PVTP|16357|20260426|CLASSIC": {
      "venue": "PVR: Preston, Gachibowli Hyderabad",
      "time": "10:30 PM",
      "date": "20260426",
      "cat": "CLASSIC",
      "price": "295.00",
      "status": "3"
    },
    "PVHM|23023|20260426|RECLINER": {
      "venue": "PVR ICON: Hitech, Madhapur, Hyderabad",
      "time": "11:20 AM",
      "date": "20260426",
      "cat": "RECLINER",
      "price": "350.00",
      "status": "3"
    },
    "PVHM|23023|20260426|CLASSIC": {
      "venue": "PVR ICON: Hitech, Madhapur, Hyderabad",
      "time": "11:20 AM",
      "date": "20260426",
      "cat": "CLASSIC",
      "price": "295.00",
      "status": "3"
    },
    "PVHM|23025|20260426|RECLINER": {
      "venue": "PVR ICON: Hitech, Madhapur, Hyderabad",
      "time": "05:10 PM",
      "date": "20260426",
      "cat": "RECLINER",
      "price": "350.00",
      "status": "3"
    },
    "PVHM|23025|20260426|CLASSIC": {
      "venue": "PVR ICON: Hitech, Madhapur, Hyderabad",
      "time": "05:10 PM",
      "date": "20260426",
      "cat": "CLASSIC",
      "price": "295.00",
      "status": "3"
    },
    "PVHM|23026|20260426|RECLINER": {
      "venue": "PVR ICON: Hitech, Madhapur, Hyderabad",
      "time": "08:05 PM",
      "date": "20260426",
      "cat": "RECLINER",
      "price": "350.00",
      "status": "0"
    },
    "PVHM|23026|20260426|CLASSIC": {
      "venue": "PVR ICON: Hitech, Madhapur, Hyderabad",
      "time": "08:05 PM",
      "date": "20260426",
      "cat": "CLASSIC",
      "price": "295.00",
      "status": "3"
    },
    "PVHM|23027|20260426|RECLINER": {
      "venue": "PVR ICON: Hitech, Madhapur, Hyderabad",
      "time": "11:00 PM",
      "date": "20260426",
      "cat": "RECLINER",
      "price": "350.00",
      "status": "0"
    },
    "PVHM|23027|20260426|CLASSIC": {
      "venue": "PVR ICON: Hitech, Madhapur, Hyderabad",
      "time": "11:00 PM",
      "date": "20260426",
      "cat": "CLASSIC",
      "price": "295.00",
      "status": "3"
    },
    "PVUM|24548|20260426|RECLINER": {
      "venue": "PVR: Musarambagh, Hyderabad",
      "time": "11:20 AM",
      "date": "20260426",
      "cat": "RECLINER",
      "price": "350.00",
      "status": "3"
    },
    "PVUM|24548|20260426|CLASSIC": {
      "venue": "PVR: Musarambagh, Hyderabad",
      "time": "11:20 AM",
      "date": "20260426",
      "cat": "CLASSIC",
      "price": "295.00",
      "status": "3"
    },
    "PVUM|24550|20260426|RECLINER": {
      "venue": "PVR: Musarambagh, Hyderabad",
      "time": "05:10 PM",
      "date": "20260426",
      "cat": "RECLINER",
      "price": "350.00",
      "status": "3"
    },
    "PVUM|24550|20260426|CLASSIC": {
      "venue": "PVR: Musarambagh, Hyderabad",
      "time": "05:10 PM",
      "date": "20260426",
      "cat": "CLASSIC",
      "price": "295.00",
      "status": "3"
    },
    "PVUM|24551|20260426|RECLINER": {
      "venue": "PVR: Musarambagh, Hyderabad",
      "time": "08:05 PM",
      "date": "20260426",
      "cat": "RECLINER",
      "price": "350.00",
      "status": "3"
    },
    "PVUM|24551|20260426|CLASSIC": {
      "venue": "PVR: Musarambagh, Hyderabad",
      "time": "08:05 PM",
      "date": "20260426",
      "cat": "CLASSIC",
      "price": "295.00",
      "status": "3"
    },
    "PVUM|24552|20260426|RECLINER": {
      "venue": "PVR: Musarambagh, Hyderabad",
      "time": "11:00 PM",
      "date": "20260426",
      "cat": "RECLINER",
      "price": "350.00",
      "status": "3"
    },
    "PVUM|24552|20260426|CLASSIC": {
      "venue": "PVR: Musarambagh, Hyderabad",
      "time": "11:00 PM",
      "date": "20260426",
      "cat": "CLASSIC",
      "price": "295.00",
      "status": "3"
    }
  },
  "dates": {
    "20260423": "AVAILABLE",
    "20260424": "AVAILABLE",
    "20260425": "AVAILABLE",
    "20260426": "BOOKABLE",
    "20260427": "AVAILABLE",
    "20260428": "AVAILABLE",
    "20260429": "AVAILABLE"
  }
}